{
  "id": "tbl7JIUHTMA3nCAAGIW",
  "name": "Currencies",
  "description": null,
  "dbTableName": "\"bseTIY0IrZr61kt6u5E\".\"Currencies\"",
  "fields": [
    {
      "id": "fldmavvIAMlfJKVMeAU",
      "name": "Name",
      "dbFieldName": "Name",
      "type": "singleLineText",
      "description": null,
      "options": {},
      "cellValueType": "string",
      "isLookup": null,
      "isComputed": null,
      "isMultipleCellValue": null
    },
    {
      "id": "fld6VEWezJVquMkBoPf",
      "name": "Status",
      "dbFieldName": "Status",
      "type": "singleSelect",
      "description": null,
      "options": [
        "Acitve",
        "Inactive"
      ],
      "cellValueType": "string",
      "isLookup": null,
      "isComputed": null,
      "isMultipleCellValue": null
    },
    {
      "id": "fldaQybVaE1UNmKXRs5",
      "name": "Symbol",
      "dbFieldName": "Symbol",
      "type": "singleLineText",
      "description": null,
      "options": {},
      "cellValueType": "string",
      "isLookup": null,
      "isComputed": null,
      "isMultipleCellValue": null
    },
    {
      "id": "fldmURHNiaqbVJbgl4o",
      "name": "Unit",
      "dbFieldName": "Unit",
      "type": "number",
      "description": null,
      "options": {
        "formatting": {
          "precision": 0,
          "type": "decimal"
        }
      },
      "cellValueType": "number",
      "isLookup": null,
      "isComputed": null,
      "isMultipleCellValue": null
    },
    {
      "id": "fldb4UMM96vJbBy0dmW",
      "name": "ID",
      "dbFieldName": "ID",
      "type": "autoNumber",
      "description": null,
      "options": {
        "expression": "AUTO_NUMBER()"
      },
      "cellValueType": "number",
      "isLookup": null,
      "isComputed": true,
      "isMultipleCellValue": null
    },
    {
      "id": "fldU8RQ9KSd5eseZm2e",
      "name": "Code",
      "dbFieldName": "Code",
      "type": "singleLineText",
      "description": null,
      "options": {},
      "cellValueType": "string",
      "isLookup": null,
      "isComputed": null,
      "isMultipleCellValue": null
    }
  ]
}
